friendly_deprecation_test-2.0.0.dist-info/DESCRIPTION.rst
friendly_deprecation_test-2.0.0.dist-info/METADATA
friendly_deprecation_test-2.0.0.dist-info/RECORD
friendly_deprecation_test-2.0.0.dist-info/WHEEL
friendly_deprecation_test-2.0.0.dist-info/metadata.json
friendly_deprecation_test-2.0.0.dist-info/top_level.txt
friends/__init__.py
