Metadata-Version: 2.0
Name: friendly-deprecation-test
Version: 2.0.0
Summary: Testing phasing out Python runtimes
Home-page: https://github.com/tonybaloney/friendly-deprecation-test
Author: Anthony Shaw
Author-email: anthonyshaw@apache.org
License: UNKNOWN
Platform: UNKNOWN
Classifier: Programming Language :: Python :: 3
Classifier: Programming Language :: Python :: 3.3
Classifier: Programming Language :: Python :: 3.4
Classifier: Programming Language :: Python :: 3.5
Classifier: Programming Language :: Python :: 3.6
Requires-Python: >=3
